jupytercad_lab/__init__.py
jupytercad_lab/_version.py
jupytercad_lab/notebook/__init__.py
jupytercad_lab/notebook/cad_document.py
jupytercad_lab/notebook/utils.py
jupytercad_lab/notebook/y_connector.py
jupytercad_lab-3.4.0.data/data/share/jupyter/labextensions/@jupytercad/jupytercad-lab/package.json
jupytercad_lab-3.4.0.data/data/share/jupyter/labextensions/@jupytercad/jupytercad-lab/static/432.36626b6a3d2d28a6ca67.js
jupytercad_lab-3.4.0.data/data/share/jupyter/labextensions/@jupytercad/jupytercad-lab/static/484.a2281518690b3fc80890.js
jupytercad_lab-3.4.0.data/data/share/jupyter/labextensions/@jupytercad/jupytercad-lab/static/500.061c268d16dc522c66b2.js
jupytercad_lab-3.4.0.data/data/share/jupyter/labextensions/@jupytercad/jupytercad-lab/static/remoteEntry.dfea4837111aeaa84bdf.js
jupytercad_lab-3.4.0.data/data/share/jupyter/labextensions/@jupytercad/jupytercad-lab/static/style.js
jupytercad_lab-3.4.0.data/data/share/jupyter/labextensions/@jupytercad/jupytercad-lab/static/third-party-licenses.json
jupytercad_lab-3.4.0.data/data/share/jupyter/labextensions/@jupytercad/jupytercad-lab/install.json
jupytercad_lab-3.4.0.dist-info/METADATA
jupytercad_lab-3.4.0.dist-info/WHEEL
jupytercad_lab-3.4.0.dist-info/licenses/LICENSE
jupytercad_lab-3.4.0.dist-info/RECORD
