Metadata-Version: 2.4
Name: jupytercad_lab
Version: 3.4.0
Dynamic: Keywords
Summary: JupyterCad Lab extension.
Project-URL: Homepage, https://github.com/jupytercad/JupyterCAD
Project-URL: Bug Tracker, https://github.com/jupytercad/JupyterCAD/issues
Project-URL: Repository, https://github.com/jupytercad/JupyterCAD.git
Author: JupyterCad contributors
License: BSD 3-Clause License
License-File: LICENSE
Classifier: Framework :: Jupyter
Classifier: Framework :: Jupyter :: JupyterLab
Classifier: Framework :: Jupyter :: JupyterLab :: 4
Classifier: Framework :: Jupyter :: JupyterLab :: Extensions
Classifier: Framework :: Jupyter :: JupyterLab :: Extensions :: Prebuilt
Classifier: License :: OSI Approved :: BSD License
Classifier: Programming Language :: Python
Classifier: Programming Language :: Python :: 3
Classifier: Programming Language :: Python :: 3.8
Classifier: Programming Language :: Python :: 3.9
Classifier: Programming Language :: Python :: 3.10
Classifier: Programming Language :: Python :: 3.11
Classifier: Programming Language :: Python :: 3.12
Classifier: Programming Language :: Python :: 3.13
Classifier: Programming Language :: Python :: 3.14
Requires-Python: >=3.8
Requires-Dist: comm<0.2.0,>=0.1.2
Requires-Dist: jupytercad-core<4,>=3.0.0a0
Requires-Dist: pycrdt
Requires-Dist: pydantic<3,>=2
Requires-Dist: yjs-widgets<0.5,>=0.4
Requires-Dist: ypywidgets<0.10.0,>=0.9.0
